src/__init__.py
src/password_generator.py
src/weighted_average.py
test/__init__.py
test/test_password_generator.py
test/test_weighted_average.py
mk_tools-0.2.1.dist-info/LICENSE
mk_tools-0.2.1.dist-info/METADATA
mk_tools-0.2.1.dist-info/WHEEL
mk_tools-0.2.1.dist-info/top_level.txt
mk_tools-0.2.1.dist-info/RECORD
