Metadata-Version: 2.1
Name: mk_tools
Version: 0.2.1
License-File: LICENSE
Requires-Dist: pandas ==2.2.3
